MANIFEST.in
README.md
pyproject.toml
requirements.txt
setup.py
mindsdb_streams/__about__.py
mindsdb_streams/__init__.py
mindsdb_streams/stream_controller.py
mindsdb_streams.egg-info/PKG-INFO
mindsdb_streams.egg-info/SOURCES.txt
mindsdb_streams.egg-info/dependency_links.txt
mindsdb_streams.egg-info/requires.txt
mindsdb_streams.egg-info/top_level.txt
mindsdb_streams/base/__init__.py
mindsdb_streams/base/base_stream.py
mindsdb_streams/kafka_stream/__init__.py
mindsdb_streams/kafka_stream/kafka_stream.py
mindsdb_streams/redis_stream/__init__.py
mindsdb_streams/redis_stream/redis_stream.py
mindsdb_streams/test_stream/__init__.py
mindsdb_streams/test_stream/test_stream.py
mindsdb_streams/utils/__init__.py
mindsdb_streams/utils/cache.py
tests/__init__.py
tests/test_streams.py